hyper_models/__init__.py
hyper_models/loader.py
hyper_models/models.py
hyper_models/preprocessing.py
hyper_models/registry.py
hyper_models-0.1.0.dist-info/METADATA
hyper_models-0.1.0.dist-info/WHEEL
hyper_models-0.1.0.dist-info/licenses/LICENSE
hyper_models-0.1.0.dist-info/RECORD
