Metadata-Version: 2.4
Name: hyper-models
Version: 0.1.0
Summary: A model zoo for non-Euclidean embedding models (hyperbolic, spherical, product manifolds)
Project-URL: Homepage, https://github.com/Hyper3Labs/hyper-models
Project-URL: Repository, https://github.com/Hyper3Labs/hyper-models
Project-URL: Documentation, https://github.com/Hyper3Labs/hyper-models#readme
Project-URL: Issues, https://github.com/Hyper3Labs/hyper-models/issues
Author: Hyper3Labs
License: MIT
License-File: LICENSE
Keywords: clip,embeddings,hyperbolic,model-zoo,non-euclidean,onnx
Classifier: Development Status :: 3 - Alpha
Classifier: Intended Audience :: Developers
Classifier: Intended Audience :: Science/Research
Classifier: License :: OSI Approved :: MIT License
Classifier: Programming Language :: Python :: 3
Classifier: Programming Language :: Python :: 3.10
Classifier: Programming Language :: Python :: 3.11
Classifier: Programming Language :: Python :: 3.12
Classifier: Topic :: Scientific/Engineering :: Artificial Intelligence
Requires-Python: >=3.10
Requires-Dist: huggingface-hub>=1.0
Requires-Dist: numpy>=1.26
Requires-Dist: onnxruntime>=1.20
Requires-Dist: pillow>=10.0
Provides-Extra: dev
Requires-Dist: pytest>=7.0; extra == 'dev'
Requires-Dist: ruff>=0.1; extra == 'dev'
